{
    "user-info": {
        "data": {
            "address": {
                "country": {},
                "formatted": "\n\n  \n",
                "locality": "",
                "postal_code": "",
                "region": {},
                "street_address": ""
            },
            "child_company_ids": [
                {
                    "id": 65,
                    "name": "RMA Building"
                },
                {
                    "id": 63,
                    "name": "Water Mark Building"
                }
            ],
            "company_id": {
                "id": 63,
                "name": "Water Mark Building"
            },
            "company_ids": [
                62,
                65,
                63
            ],
            "company_tz": "Asia/Calcutta",
            "email": "rajahr@gmail.com",
            "employee": {
                "id": 6235,
                "name": "Raja"
            },
            "locale": "en_US",
            "name": "Raja",
            "phone_number": "",
            "updated_at": "2020-08-01 02:44:08",
            "user_id": 1114,
            "user_role": "tenant_hr",
            "username": "rajahr@gmail.com",
            "vendor": {
                "id": 1450,
                "name": "Motivity Labs(Tenant)"
            },
            "website": "",
            "zoneinfo": "Asia/Kolkata"
        },
        "error": {},
        "length": 0,
        "status": true
    },
    "token": {
        "access_token": "zrAAOGdrmvekg24sZpisMoBTA0GjjH",
        "expires_in": 3600,
        "token_type": "Bearer",
        "scope": "",
        "refresh_token": "dajeNuqrlA4Vwh36vdkjFTFAs9i1zs"
    }
}